LICENSE
README.md
requirements.txt
setup.py
knowsmore/__init__.py
knowsmore/__main__.py
knowsmore/__meta__.py
knowsmore/args.py
knowsmore/cmdbase.py
knowsmore/config.py
knowsmore/knowsmore.py
knowsmore/module.py
knowsmore/password.py
knowsmore.egg-info/PKG-INFO
knowsmore.egg-info/SOURCES.txt
knowsmore.egg-info/dependency_links.txt
knowsmore.egg-info/entry_points.txt
knowsmore.egg-info/not-zip-safe
knowsmore.egg-info/requires.txt
knowsmore.egg-info/top_level.txt
knowsmore/cmd/__init__.py
knowsmore/cmd/bloodhound.py
knowsmore/cmd/createdb.py
knowsmore/cmd/credentials.py
knowsmore/cmd/export.py
knowsmore/cmd/find.py
knowsmore/cmd/hashes.py
knowsmore/cmd/memberof.py
knowsmore/cmd/precomputed.py
knowsmore/cmd/secretsdump.py
knowsmore/cmd/splunk.py
knowsmore/cmd/stats.py
knowsmore/cmd/userpass.py
knowsmore/cmd/wipe.py
knowsmore/cmd/wordlist.py
knowsmore/libs/__init__.py
knowsmore/libs/bloodhoundsync.py
knowsmore/libs/exporterbase.py
knowsmore/libs/ntdsuseraccount.py
knowsmore/libs/secretsdump.py
knowsmore/util/__init__.py
knowsmore/util/color.py
knowsmore/util/database.py
knowsmore/util/knowsmoredb.py
knowsmore/util/logger.py
knowsmore/util/process.py
knowsmore/util/tools.py