Metadata-Version: 2.1
Name: knowsmore
Version: 0.1.46
Summary: KnowsMore is a swiss army knife tool for pentesting Microsoft Active Directory (NTLM Hashes, BloodHound, NTDS and DCSync).
Home-page: https://github.com/helviojunior/knowsmore
Author: Helvio Junior  (M4v3r1ck)
Author-email: helvio.junior@sec4us.com.br
License: GPL-3.0
Project-URL: Main Author, https://sec4us.com.br/instrutores/helvio-junior/
Project-URL: Documentation, https://github.com/helviojunior/knowsmore
Project-URL: Source, https://github.com/helviojunior/knowsmore
Classifier: Development Status :: 5 - Production/Stable
Classifier: Environment :: Console
Classifier: Intended Audience :: System Administrators
Classifier: License :: OSI Approved :: GNU General Public License v3 (GPLv3)
Classifier: Natural Language :: English
Classifier: Operating System :: OS Independent
Classifier: Programming Language :: Python
Classifier: Programming Language :: Python :: 3
Classifier: Programming Language :: Python :: 3.8
Classifier: Programming Language :: Python :: 3.9
Classifier: Programming Language :: Python :: 3.10
Classifier: Programming Language :: Python :: 3.11
Classifier: Programming Language :: Python :: 3 :: Only
Classifier: Programming Language :: Python :: Implementation :: PyPy
Classifier: Topic :: Security
Classifier: Topic :: System :: Networking
Classifier: Topic :: System :: Operating System
Classifier: Topic :: System :: Systems Administration
Classifier: Topic :: Utilities
Requires-Python: >=3.8, <4
License-File: LICENSE
